transformix/__init__.py
transformix/core.py
transformix-1.1.0.dist-info/licenses/LICENSE
transformix-1.1.0.dist-info/METADATA
transformix-1.1.0.dist-info/WHEEL
transformix-1.1.0.dist-info/top_level.txt
transformix-1.1.0.dist-info/RECORD
