Metadata-Version: 2.4
Name: transformix
Version: 1.1.0
Summary: A Python wrapper for transformix
Author-email: Jasper Phelps <jasper.s.phelps@gmail.com>
License:                     GNU GENERAL PUBLIC LICENSE
Project-URL: Repository, https://github.com/jasper-tms/pytransformix
Keywords: transformix,elastix,elastic,non-rigid,registration,alignment,warping
Classifier: Programming Language :: Python :: 3
Classifier: Intended Audience :: Science/Research
Classifier: License :: OSI Approved :: GNU General Public License v3 or later (GPLv3+)
Classifier: Operating System :: MacOS
Classifier: Operating System :: POSIX :: Linux
Requires-Python: >=3.6
License-File: LICENSE
Requires-Dist: numpy
Requires-Dist: numpyimage
Dynamic: license-file
